odoo_backup/__init__.py
odoo_backup_cli-1.0.3.dist-info/METADATA
odoo_backup_cli-1.0.3.dist-info/WHEEL
odoo_backup_cli-1.0.3.dist-info/entry_points.txt
odoo_backup_cli-1.0.3.dist-info/top_level.txt
odoo_backup_cli-1.0.3.dist-info/RECORD
