Metadata-Version: 2.1
Name: odoo-backup-cli
Version: 1.0.3
Summary: Odoo backup tool
Home-page: UNKNOWN
Author: Omar Diaz
Author-email: zcool2005@gmail.com
License: UNKNOWN
Platform: UNKNOWN
Requires-Dist: Click
Requires-Dist: requests
Requires-Dist: minio
